pyICMP/__init__.py
pyICMP-1.0.1.dist-info/LICENSE
pyICMP-1.0.1.dist-info/METADATA
pyICMP-1.0.1.dist-info/WHEEL
pyICMP-1.0.1.dist-info/top_level.txt
pyICMP-1.0.1.dist-info/RECORD
