Metadata-Version: 2.1
Name: pyICMP
Version: 1.0.1
Summary: A ping client for python
Home-page: https://github.com/AndersBallegaard/pyICMP
Author: Anders Ballegaard
Author-email: anderstb@hotmail.dk
License: UNKNOWN
Platform: UNKNOWN
Classifier: Programming Language :: Python :: 3
Classifier: License :: OSI Approved :: MIT License
Classifier: Operating System :: OS Independent
